{
    "type": "FeatureCollection",
    "features": [
        {
            "type": "Feature",
            "geometry": {
                "type": "Point",
                "coordinates": [
                    -78.02123756162464,
                    8.561841711739403
                ]
            },
            "properties": {
                "name": "Migrant Reception Station: San Vicente"
            }
        }
    ]
}